toololo/__init__.py
toololo/chat.py
toololo/function.py
toololo/function_examples.py
toololo/run.py
toololo/types.py
toololo-0.5.0.dist-info/licenses/LICENSE
toololo-0.5.0.dist-info/METADATA
toololo-0.5.0.dist-info/WHEEL
toololo-0.5.0.dist-info/top_level.txt
toololo-0.5.0.dist-info/RECORD
