Metadata-Version: 2.4
Name: toololo
Version: 0.5.0
Summary: Minimal Python function calling for Claude and OpenRouter
Home-page: https://github.com/andreasjansson/toololo
Author: Andreas Jansson
Classifier: Programming Language :: Python :: 3
Classifier: License :: OSI Approved :: MIT License
Classifier: Operating System :: OS Independent
Requires-Python: >=3.7
License-File: LICENSE
Requires-Dist: openai<2,>=1.0.0
Dynamic: author
Dynamic: classifier
Dynamic: description
Dynamic: description-content-type
Dynamic: home-page
Dynamic: license-file
Dynamic: requires-dist
Dynamic: requires-python
Dynamic: summary
